src/__init__.py
src/main.py
artgriddownloader-0.1.0.dist-info/entry_points.txt
artgriddownloader-0.1.0.dist-info/METADATA
artgriddownloader-0.1.0.dist-info/WHEEL
artgriddownloader-0.1.0.dist-info/RECORD
